LICENSE
MANIFEST.in
README.md
setup.cfg
setup.py
amara3.xml.egg-info/PKG-INFO
amara3.xml.egg-info/SOURCES.txt
amara3.xml.egg-info/dependency_links.txt
amara3.xml.egg-info/requires.txt
amara3.xml.egg-info/top_level.txt
clib/charset.h
clib/xmlstring.c
clib/xmlstring.h
doc/index.md
exec/microx
pylib/uxml/__init__.py
pylib/uxml/coax.py
pylib/uxml/html5.py
pylib/uxml/html5iter.py
pylib/uxml/lex.py
pylib/uxml/parser.py
pylib/uxml/tree.py
pylib/uxml/treeiter.py
pylib/uxml/treeutil.py
pylib/uxml/version.py
pylib/uxml/writer.py
pylib/uxml/xml.py
pylib/uxml/xmliter.py
pylib/uxml/uxpath/__init__.py
pylib/uxml/uxpath/functions.py
pylib/uxml/uxpath/lexrules.py
pylib/uxml/uxpath/parserules.py
pylib/uxml/uxpath/xast.py
test/conftest.py
test/uxml/spectest1.uxml
test/uxml/test1.uxml
test/uxml/test_chunk_parse_write.py
test/uxml/test_html5.py
test/uxml/test_parser.py
test/uxml/test_tree.py
test/uxml/test_treegc.py
test/uxml/test_treeiter.py
test/uxml/test_treeutil.py
test/uxml/test_uxpath.py
test/uxml/test_writer.py