Metadata-Version: 2.4
Name: amara3.xml
Version: 3.4.1
Summary: Amara3 project, which offers a variety of data processing tools. This module adds the MicroXML support, and adaptation to classic XML.
Home-page: https://github.com/uogbuji/amara3-xml
Author: Uche Ogbuji
Author-email: uche@ogbuji.net
License: License :: OSI Approved :: Apache Software License
Keywords: xml,web,data
Classifier: Programming Language :: Python
Classifier: Programming Language :: Python :: 3
Classifier: Development Status :: 4 - Beta
Classifier: Intended Audience :: Developers
Classifier: License :: OSI Approved :: Apache Software License
Classifier: Operating System :: OS Independent
Classifier: Topic :: Software Development :: Libraries :: Python Modules
Classifier: Topic :: Internet :: WWW/HTTP
License-File: LICENSE
Requires-Dist: amara3.iri>=3.0.1
Requires-Dist: nameparser
Requires-Dist: pytest
Requires-Dist: ply
Requires-Dist: html5lib
Dynamic: author
Dynamic: author-email
Dynamic: classifier
Dynamic: description
Dynamic: description-content-type
Dynamic: home-page
Dynamic: keywords
Dynamic: license
Dynamic: license-file
Dynamic: requires-dist
Dynamic: summary
